respectscraper-0.1.2.dist-info/licenses/LICENSE
respectscraper-0.1.2.dist-info/licenses/LICENSE_HEADER.txt
respectscraper-0.1.2.dist-info/licenses/NOTICE
webscraper/__init__.py
webscraper/api_client.py
webscraper/cli.py
webscraper/core.py
webscraper/file_extractor.py
webscraper/llm_client.py
webscraper/robots_checker.py
webscraper/utils.py
respectscraper-0.1.2.dist-info/METADATA
respectscraper-0.1.2.dist-info/WHEEL
respectscraper-0.1.2.dist-info/entry_points.txt
respectscraper-0.1.2.dist-info/top_level.txt
respectscraper-0.1.2.dist-info/RECORD
