Metadata-Version: 2.4
Name: respectscraper
Version: 0.1.2
Summary: Ethical web scraper with robots.txt compliance, AI-powered interpretation, and comprehensive content extraction
Author-email: Zakhele Gamede <info@zakhelegamede.com>
License-Expression: Apache-2.0
Project-URL: Homepage, https://github.com/Zakhele-TechWannabe/respectscraper
Project-URL: Repository, https://github.com/Zakhele-TechWannabe/respectscraper.git
Project-URL: Issues, https://github.com/Zakhele-TechWannabe/respectscraper/issues
Project-URL: Documentation, https://github.com/Zakhele-TechWannabe/respectscraper/wiki
Keywords: webscraper,scraping,robots.txt,pdf,excel,word,ai,llm,ethical,respectful
Classifier: Development Status :: 4 - Beta
Classifier: Intended Audience :: Developers
Classifier: Operating System :: OS Independent
Classifier: Programming Language :: Python :: 3.11
Classifier: Programming Language :: Python :: 3.12
Classifier: Topic :: Internet :: WWW/HTTP :: Indexing/Search
Classifier: Topic :: Software Development :: Libraries :: Python Modules
Classifier: Topic :: Text Processing :: Markup :: HTML
Classifier: Topic :: Utilities
Requires-Python: >=3.8
License-File: LICENSE
License-File: LICENSE_HEADER.txt
License-File: NOTICE
Requires-Dist: requests>=2.32.3
Requires-Dist: beautifulsoup4>=4.13.4
Requires-Dist: lxml>=6.0.0
Requires-Dist: PyPDF2>=3.0.1
Requires-Dist: openpyxl>=3.1.5
Requires-Dist: python-docx>=1.2.0
Requires-Dist: urllib3>=2.5.0
Requires-Dist: openai>=1.66.3
Requires-Dist: anthropic>=0.61.0
Requires-Dist: pyrate-limiter>=3.9.0
Requires-Dist: aiohttp>=3.12.15
Requires-Dist: aiofiles>=24.1.0
Requires-Dist: tqdm>=4.67.1
Requires-Dist: colorama>=0.4.6
Provides-Extra: dev
Requires-Dist: pytest>=7.0.0; extra == "dev"
Requires-Dist: pytest-asyncio>=0.21.0; extra == "dev"
Requires-Dist: black>=22.0.0; extra == "dev"
Requires-Dist: flake8>=5.0.0; extra == "dev"
Requires-Dist: mypy>=0.991; extra == "dev"
Dynamic: license-file
